faas_cache_dict/__init__.py
faas_cache_dict/constants.py
faas_cache_dict/exceptions.py
faas_cache_dict/faas_cache_dict.py
faas_cache_dict/size_utils.py
faas_cache_dict/utils.py
faas_cache_dict-0.7.0.dist-info/LICENSE
faas_cache_dict-0.7.0.dist-info/METADATA
faas_cache_dict-0.7.0.dist-info/WHEEL
faas_cache_dict-0.7.0.dist-info/top_level.txt
faas_cache_dict-0.7.0.dist-info/RECORD
