Metadata-Version: 2.1
Name: faas-cache-dict
Version: 0.7.0
Summary: A Python dictionary implementation designed to act as an in-memory cache for FaaS environments
Home-page: https://github.com/juanjsebgarcia/faas-cache-dict
Author: Juan Garcia Alvite
License: MIT
Classifier: License :: OSI Approved :: MIT License
Classifier: Programming Language :: Python :: 3
Classifier: Programming Language :: Python :: 3.9
Classifier: Programming Language :: Python :: 3.10
Classifier: Programming Language :: Python :: 3.11
Classifier: Programming Language :: Python :: 3.12
Classifier: Programming Language :: Python :: 3.13
Requires-Python: >=3.9
License-File: LICENSE
Requires-Dist: objsize ==0.7.1
